django_xml-4.0.0.dist-info/licenses/LICENSE
djxml/__init__.py
django_xml-4.0.0.dist-info/METADATA
django_xml-4.0.0.dist-info/WHEEL
django_xml-4.0.0.dist-info/top_level.txt
django_xml-4.0.0.dist-info/RECORD
